paintbox/__init__.py
paintbox/_astropy_init.py
paintbox/conftest.py
paintbox/extlaws.py
paintbox/interfaces.py
paintbox/likelihoods.py
paintbox/operators.py
paintbox/sed.py
paintbox/version.py
paintbox/utils/CvD_utils.py
paintbox/utils/__init__.py
paintbox/utils/convolve.py
paintbox/utils/disp2vel.py
paintbox/utils/lick.py
paintbox/utils/theano_loglike.py
paintbox-1.2.dist-info/LICENSE.rst
paintbox-1.2.dist-info/METADATA
paintbox-1.2.dist-info/WHEEL
paintbox-1.2.dist-info/entry_points.txt
paintbox-1.2.dist-info/top_level.txt
paintbox-1.2.dist-info/RECORD
