Metadata-Version: 2.1
Name: paintbox
Version: 1.2
Summary: Paintbox
Home-page: http://github.com/cebarbosa/paintbox
Author: Carlos Eduardo Barbosa
Author-email: kadu.barbosa@gmail.com
License: BSD 3-Clause
Platform: UNKNOWN
Requires-Python: >=3.7
Requires-Dist: astropy
Requires-Dist: numpy
Requires-Dist: scipy
Requires-Dist: spectres
Provides-Extra: all
Requires-Dist: scipy ; extra == 'all'
Requires-Dist: numpy ; extra == 'all'
Requires-Dist: sphinx-astropy ; extra == 'all'
Requires-Dist: matplotlib ; extra == 'all'
Requires-Dist: theano ; extra == 'all'
Provides-Extra: docs
Requires-Dist: sphinx-astropy ; extra == 'docs'
Provides-Extra: test
Requires-Dist: pytest-astropy ; extra == 'test'
